cagraph/__init__.py
cagraph/_version.py
cagraph/cagraph.py
cagraph/preprocess.py
cagraph/visualization.py
cagraph-0.0.17.dist-info/METADATA
cagraph-0.0.17.dist-info/WHEEL
cagraph-0.0.17.dist-info/licenses/LICENSE
cagraph-0.0.17.dist-info/RECORD
